reactipy/__init__.py
reactipy/component.py
reactipy/exceptions.py
reactipy/node_env.py
reactipy/package.json
reactipy/reactipy.js
reactipy/settings.py
reactipy/start.py
reactipy/tests/__init__.py
reactipy/tests/test.py
reactipy/tests/test_functionality.py
reactipy/tests/test_performance.py
ReactiPy-0.1.1.dist-info/DESCRIPTION.rst
ReactiPy-0.1.1.dist-info/METADATA
ReactiPy-0.1.1.dist-info/metadata.json
ReactiPy-0.1.1.dist-info/RECORD
ReactiPy-0.1.1.dist-info/top_level.txt
ReactiPy-0.1.1.dist-info/WHEEL
