Metadata-Version: 2.0
Name: ReactiPy
Version: 0.1.1
Summary: Compiles React Components server side using python
Home-page: https://github.com/logandhead/ReactiPy
Author: Logan Head
Author-email: logandhead@gmail.com
License: MIT
Keywords: react jsx compile react.js reactjs facebook
Platform: UNKNOWN
Classifier: Development Status :: 3 - Alpha
Classifier: Intended Audience :: Developers
Classifier: Topic :: Software Development :: Build Tools
Classifier: License :: OSI Approved :: MIT License
Requires-Dist: nodeenv (==0.13.1)
